dreamgraph
