Metadata-Version: 1.1
Name: dreamgraph
Version: 1.0.8
Summary: The Python module for Telegraph API
Home-page: https://github.com/JasurbekNURBOYEV/DreamGraph
Author: Jasur Nurboev
Author-email: bluestacks6523@gmail.com
License: UNKNOWN
Download-URL: https://github.com/JasurbekNURBOYEV/DreamGraph/archive/1.0.8.tar.gz
Keywords: telegraph,telegraph-api,python-module,dreamgraph
Platform: UNKNOWN
